SampicTCPController/HostMachineServer.py
SampicTCPController/SampicTCPController.py
SampicTCPController/__init__.py
sampictcpcontroller-0.0.2.dist-info/licenses/LICENSE
sampictcpcontroller-0.0.2.dist-info/METADATA
sampictcpcontroller-0.0.2.dist-info/WHEEL
sampictcpcontroller-0.0.2.dist-info/top_level.txt
sampictcpcontroller-0.0.2.dist-info/RECORD
