Metadata-Version: 2.4
Name: SampicTCPController
Version: 0.0.2
Summary: A Python tool to control a Sampic data acquisition through the TCP protocol
Author-email: Laurent Forthomme <laurent.forthomme@cern.ch>
License-Expression: GPL-3.0-or-later
Project-URL: Homepage, https://gitlab.cern.ch/h8ctb/SampicTCPController
Keywords: sampic,oscilloscope,waveform
Classifier: Programming Language :: Python
Classifier: Programming Language :: Python :: 3
Classifier: Topic :: Scientific/Engineering :: Information Analysis
Requires-Python: >=3.1
License-File: LICENSE
Requires-Dist: numpy
Provides-Extra: dev
Requires-Dist: black; extra == "dev"
Requires-Dist: bumpver; extra == "dev"
Requires-Dist: isort; extra == "dev"
Requires-Dist: pip-tools; extra == "dev"
Requires-Dist: pytest; extra == "dev"
Dynamic: license-file
